ageml/__init__.py
ageml/__main__.py
ageml/commands.py
ageml/datasets/.gitkeep
ageml/datasets/__init__.py
ageml/datasets/generate_synthetic_data.py
ageml/datasets/synthetic_data.py
ageml/datasets/toy_clinical.csv
ageml/datasets/toy_covar.csv
ageml/datasets/toy_factors.csv
ageml/datasets/toy_features.csv
ageml/datasets/toy_systems.txt
ageml/messages.py
ageml/modelling.py
ageml/processing.py
ageml/ui.py
ageml/utils.py
ageml/visualizer.py
ageml-0.3.0.dist-info/LICENSE
ageml-0.3.0.dist-info/METADATA
ageml-0.3.0.dist-info/WHEEL
ageml-0.3.0.dist-info/entry_points.txt
ageml-0.3.0.dist-info/RECORD
