Metadata-Version: 2.1
Name: ageml
Version: 0.3.0
Summary: AgeML is a Python package for Age Modelling with Machine Learning made easy.
Home-page: https://github.com/compneurobilbao/ageml
License: Apache 2.0
Keywords: Machine Learning,Age Modelling,Brain Age
Author: Computational Neuroimaging Lab Bilbao, IIS Biobizkaia
Maintainer: inigo.tellaetxe
Maintainer-email: inigotellaetxe@gmail.com
Requires-Python: >=3.9,<3.12
Classifier: License :: Other/Proprietary License
Classifier: Programming Language :: Python :: 3
Classifier: Programming Language :: Python :: 3.9
Classifier: Programming Language :: Python :: 3.10
Classifier: Programming Language :: Python :: 3.11
Classifier: Topic :: Software Development :: Libraries :: Python Modules
Requires-Dist: hpsklearn-compneurobilbao
Requires-Dist: matplotlib (==3.5)
Requires-Dist: numpy (>=1.24,<2.0.0)
Requires-Dist: pandas (>=2.0.2)
Requires-Dist: pillow (>=10.3.0,<11.0.0)
Requires-Dist: scikit-learn (==1.3)
Requires-Dist: scipy (>=1.10)
Requires-Dist: statsmodels (==0.14.0)
Requires-Dist: xgboost (>=2.0.3,<3.0.0)
Project-URL: Repository, https://github.com/compneurobilbao/ageml
